django_eha_sdk/__init__.py
django_eha_sdk/admin.py
django_eha_sdk/apps.py
django_eha_sdk/context_processors.py
django_eha_sdk/unittest.py
django_eha_sdk/utils.py
django_eha_sdk/auth/__init__.py
django_eha_sdk/auth/utils.py
django_eha_sdk/auth/views.py
django_eha_sdk/auth/apptoken/__init__.py
django_eha_sdk/auth/apptoken/admin.py
django_eha_sdk/auth/apptoken/apps.py
django_eha_sdk/auth/apptoken/decorators.py
django_eha_sdk/auth/apptoken/models.py
django_eha_sdk/auth/apptoken/views.py
django_eha_sdk/auth/apptoken/migrations/0001_initial.py
django_eha_sdk/auth/apptoken/migrations/__init__.py
django_eha_sdk/auth/cas/__init__.py
django_eha_sdk/auth/cas/admin.py
django_eha_sdk/auth/cas/apps.py
django_eha_sdk/auth/cas/backends.py
django_eha_sdk/auth/cas/callbacks.py
django_eha_sdk/auth/cas/models.py
django_eha_sdk/auth/cas/migrations/0001_initial.py
django_eha_sdk/auth/cas/migrations/__init__.py
django_eha_sdk/auth/keycloak/__init__.py
django_eha_sdk/auth/keycloak/forms.py
django_eha_sdk/auth/keycloak/middleware.py
django_eha_sdk/auth/keycloak/utils.py
django_eha_sdk/auth/keycloak/views.py
django_eha_sdk/conf/__init__.py
django_eha_sdk/conf/settings.py
django_eha_sdk/conf/urls.py
django_eha_sdk/drf/__init__.py
django_eha_sdk/drf/pagination.py
django_eha_sdk/drf/renderers.py
django_eha_sdk/drf/serializers.py
django_eha_sdk/health/__init__.py
django_eha_sdk/health/utils.py
django_eha_sdk/health/views.py
django_eha_sdk/management/__init__.py
django_eha_sdk/management/commands/__init__.py
django_eha_sdk/management/commands/check_url.py
django_eha_sdk/management/commands/setup_admin.py
django_eha_sdk/multitenancy/__init__.py
django_eha_sdk/multitenancy/admin.py
django_eha_sdk/multitenancy/apps.py
django_eha_sdk/multitenancy/models.py
django_eha_sdk/multitenancy/permissions.py
django_eha_sdk/multitenancy/serializers.py
django_eha_sdk/multitenancy/utils.py
django_eha_sdk/multitenancy/views.py
django_eha_sdk/multitenancy/migrations/0001_initial.py
django_eha_sdk-1.0.4.dist-info/LICENSE
django_eha_sdk-1.0.4.dist-info/METADATA
django_eha_sdk-1.0.4.dist-info/WHEEL
django_eha_sdk-1.0.4.dist-info/top_level.txt
django_eha_sdk-1.0.4.dist-info/RECORD
