Metadata-Version: 2.1
Name: django-eha-sdk
Version: 1.0.4
Summary: A python library with helpful django tools
Home-page: https://github.com/eHealthAfrica/django-eha-sdk/
Author: eHealth Africa
Author-email: info@ehealthafrica.org
License: Apache2 License
Keywords: django,setup,auth,cas,token,keycloak,multitenancy
Platform: UNKNOWN
Classifier: Development Status :: 5 - Production/Stable
Classifier: Environment :: Web Environment
Classifier: Framework :: Django :: 2.0
Classifier: Framework :: Django :: 2.1
Classifier: Framework :: Django :: 2.2
Classifier: Intended Audience :: Developers
Classifier: License :: OSI Approved :: Apache Software License
Classifier: Natural Language :: English
Classifier: Operating System :: OS Independent
Classifier: Programming Language :: Python :: 3 :: Only
Classifier: Topic :: Software Development :: Libraries :: Python Modules
Requires-Python: >=3.6
Requires-Dist: django (>=2)
Requires-Dist: django-cors-headers
Requires-Dist: django-debug-toolbar
Requires-Dist: django-prometheus
Requires-Dist: django-uwsgi
Requires-Dist: djangorestframework (>=3.8)
Requires-Dist: drf-dynamic-fields
Requires-Dist: psycopg2-binary
Requires-Dist: pygments
Requires-Dist: python-json-logger
Requires-Dist: requests
Requires-Dist: urllib3 (>=1.25)
Requires-Dist: uwsgi
Provides-Extra: cas
Requires-Dist: django-cas-ng (>=3.6) ; extra == 'cas'
Provides-Extra: scheduler
Requires-Dist: django-rq ; extra == 'scheduler'
Requires-Dist: redis ; extra == 'scheduler'
Requires-Dist: rq ; extra == 'scheduler'
Requires-Dist: rq-scheduler ; extra == 'scheduler'
Provides-Extra: server
Requires-Dist: sentry-sdk ; extra == 'server'
Provides-Extra: storage
Requires-Dist: django-minio-storage ; extra == 'storage'
Requires-Dist: django-storages[boto3,google] ; extra == 'storage'
Provides-Extra: test
Requires-Dist: coverage ; extra == 'test'
Requires-Dist: flake8 ; extra == 'test'
Requires-Dist: flake8-quotes ; extra == 'test'
Requires-Dist: tblib ; extra == 'test'
Provides-Extra: webpack
Requires-Dist: django-webpack-loader ; extra == 'webpack'
